LICENSE
setup.py
Asciin.py.egg-info/PKG-INFO
Asciin.py.egg-info/SOURCES.txt
Asciin.py.egg-info/dependency_links.txt
Asciin.py.egg-info/top_level.txt
Asciinpy/__init__.py
Asciinpy/amath.py
Asciinpy/globals.py
Asciinpy/screen.py
Asciinpy/utils.py
Asciinpy/values.py
Asciinpy/_2D/__init__.py
Asciinpy/_2D/planes.py
Asciinpy/_2D/rect.py
Asciinpy/_2D/methods/__init__.py
Asciinpy/_2D/methods/collisions.py
Asciinpy/_2D/methods/renders.py
Asciinpy/_3D/__init__.py
Asciinpy/_3D/models.py