Metadata-Version: 2.1
Name: Asciin.py
Version: 0.1.7
Summary: Featherweight 3D / 2D Ascii console game engine for Python 2.7+ with no external dependencies and in pure Python.
Home-page: https://github.com/Rickaym/Asciin.py
Author: Rickaym
License: MIT
Project-URL: Documentation, https://asciipy.readthedocs.io/en/latest/
Project-URL: Issue tracker, https://github.com/Rickaym/Asciin.py/issues
Platform: UNKNOWN
Classifier: Development Status :: 4 - Beta
Classifier: Intended Audience :: Developers
Classifier: Topic :: Multimedia :: Graphics :: 3D Modeling
Classifier: License :: OSI Approved :: MIT License
Classifier: Operating System :: OS Independent
Classifier: Natural Language :: English
Classifier: Programming Language :: Python :: 2.7
Classifier: Programming Language :: Python :: 3.9
Requires-Python: >=2.7
